blog/__init__.py
blog/admin.py
blog/apps.py
blog/models.py
blog/tests.py
blog/urls.py
blog/views.py
blog/migrations/0001_initial.py
blog/migrations/0002_comment.py
blog/migrations/0003_remove_comment_author.py
blog/migrations/0004_remove_post_author.py
blog/migrations/__init__.py
MikhailP_django_blog-0.1.dist-info/METADATA
MikhailP_django_blog-0.1.dist-info/WHEEL
MikhailP_django_blog-0.1.dist-info/top_level.txt
MikhailP_django_blog-0.1.dist-info/RECORD
