Metadata-Version: 2.1
Name: MikhailP-django-blog
Version: 0.1
Summary: A simple Django app to conduct beauty blog.
Home-page: http://wwww.hotmale.com/
Author: Mikhail Panov
Author-email: mihail52sh@mail.ru
License: MIT License
Platform: UNKNOWN
Classifier: Environment :: Web Environment
Classifier: Framework :: Django
Classifier: Intended Audience :: Developers
Classifier: License :: OSI Approved :: MIT License
Classifier: Operating System :: OS Independent
Classifier: Programming Language :: Python
Classifier: Programming Language :: Python :: 3.5
Classifier: Programming Language :: Python :: 3.6
Classifier: Topic :: Internet :: WWW/HTTP
Classifier: Topic :: Internet :: WWW/HTTP :: Dynamic Content
